<?xml version="1.0" encoding="UTF-8"?>
<openbox_config xmlns="http://openbox.org/3.4/rc">
  <resistance>
    <strength>10</strength>
    <screen_edge_strength>20</screen_edge_strength>
  </resistance>
  
  <focus>
    <focusNew>yes</focusNew>
    <followMouse>no</followMouse>
  </focus>
  
  <placement>
    <policy>Smart</policy>
    <center>yes</center>
  </placement>
  
  <theme>
    <name>Clearlooks</name>
    <titleLayout>NLIMC</titleLayout>
    <keepBorder>yes</keepBorder>
    <animateIconify>yes</animateIconify>
    <font place="ActiveWindow">
      <name>InconsolataLGC</name>
      <size>12</size>
      <weight>Bold</weight>
      <slant>Normal</slant>
    </font>
    <font place="InactiveWindow">
      <name>InconsolataLGC</name>
      <size>12</size>
      <weight>Normal</weight>
      <slant>Normal</slant>
    </font>
    <font place="MenuTitle">
      <name>InconsolataLGC</name>
      <size>12</size>
      <weight>Normal</weight>
      <slant>Normal</slant>
    </font>
    <font place="MenuItem">
      <name>InconsolataLGC</name>
      <size>12</size>
      <weight>Normal</weight>
      <slant>Normal</slant>
    </font>
  </theme>
  
  <desktops>
    <number>4</number>
    <firstdesk>1</firstdesk>
  </desktops>
  
  <keyboard>
    <chainQuitKey>C-g</chainQuitKey>
    
    <keybind key="C-A-T">
      <action name="Execute">
        <command>terminator</command>
      </action>
    </keybind>
    
    <keybind key="A-F4">
      <action name="Close"/>
    </keybind>
    
    <keybind key="A-Tab">
      <action name="NextWindow">
        <finalactions>
          <action name="Focus"/>
          <action name="Raise"/>
          <action name="Unshade"/>
        </finalactions>
      </action>
    </keybind>
    
    <keybind key="W-Up">
      <action name="Maximize"/>
    </keybind>
    
    <keybind key="W-Down">
      <action name="Unmaximize"/>
    </keybind>
  </keyboard>
  
  <mouse>
    <dragThreshold>1</dragThreshold>
    <doubleClickTime>500</doubleClickTime>
    
    <context name="Frame">
      <mousebind button="A-Left" action="Press">
        <action name="Focus"/>
        <action name="Raise"/>
      </mousebind>
      <mousebind button="A-Left" action="Drag">
        <action name="Move"/>
      </mousebind>
      <mousebind button="A-Right" action="Drag">
        <action name="Resize"/>
      </mousebind>
    </context>
    
    <context name="Titlebar">
      <mousebind button="Left" action="Drag">
        <action name="Move"/>
      </mousebind>
      <mousebind button="Left" action="DoubleClick">
        <action name="ToggleMaximize"/>
      </mousebind>
    </context>
    
    <context name="Desktop">
      <mousebind button="Middle" action="Press">
        <action name="ShowMenu">
          <menu>client-list-combined-menu</menu>
        </action>
      </mousebind>
      <mousebind button="Right" action="Press">
        <action name="ShowMenu">
          <menu>root-menu</menu>
        </action>
      </mousebind>
    </context>
  </mouse>
  
  <applications>
    <application class="*">
      <decor>yes</decor>
    </application>
  </applications>
</openbox_config>